DaShujufenxiJishuYuYingyongYizhanshiXuexiCYuyanBianchengWangFix1/README.md
DaShujufenxiJishuYuYingyongYizhanshiXuexiCYuyanBianchengWangFix1/__init__.py
DaShujufenxiJishuYuYingyongYizhanshiXuexiCYuyanBianchengWangFix1/__main__.py
DaShujufenxiJishuYuYingyongYizhanshiXuexiCYuyanBianchengWangFix1/file.epub
DaShujufenxiJishuYuYingyongYizhanshiXuexiCYuyanBianchengWangFix1/index.html
DaShujufenxiJishuYuYingyongYizhanshiXuexiCYuyanBianchengWangFix1/css/__init__.py
DaShujufenxiJishuYuYingyongYizhanshiXuexiCYuyanBianchengWangFix1/css/annotations.css
DaShujufenxiJishuYuYingyongYizhanshiXuexiCYuyanBianchengWangFix1/css/main.css
DaShujufenxiJishuYuYingyongYizhanshiXuexiCYuyanBianchengWangFix1/css/normalize.css
DaShujufenxiJishuYuYingyongYizhanshiXuexiCYuyanBianchengWangFix1/css/popup.css
DaShujufenxiJishuYuYingyongYizhanshiXuexiCYuyanBianchengWangFix1/font/__init__.py
DaShujufenxiJishuYuYingyongYizhanshiXuexiCYuyanBianchengWangFix1/font/fontello.eot
DaShujufenxiJishuYuYingyongYizhanshiXuexiCYuyanBianchengWangFix1/font/fontello.svg
DaShujufenxiJishuYuYingyongYizhanshiXuexiCYuyanBianchengWangFix1/font/fontello.ttf
DaShujufenxiJishuYuYingyongYizhanshiXuexiCYuyanBianchengWangFix1/font/fontello.woff
DaShujufenxiJishuYuYingyongYizhanshiXuexiCYuyanBianchengWangFix1/img/__init__.py
DaShujufenxiJishuYuYingyongYizhanshiXuexiCYuyanBianchengWangFix1/img/annotator-glyph-sprite.png
DaShujufenxiJishuYuYingyongYizhanshiXuexiCYuyanBianchengWangFix1/img/annotator-icon-sprite.png
DaShujufenxiJishuYuYingyongYizhanshiXuexiCYuyanBianchengWangFix1/img/apple-touch-icon.png
DaShujufenxiJishuYuYingyongYizhanshiXuexiCYuyanBianchengWangFix1/img/cancelfullscreen.png
DaShujufenxiJishuYuYingyongYizhanshiXuexiCYuyanBianchengWangFix1/img/close.png
DaShujufenxiJishuYuYingyongYizhanshiXuexiCYuyanBianchengWangFix1/img/fullscreen.png
DaShujufenxiJishuYuYingyongYizhanshiXuexiCYuyanBianchengWangFix1/img/loader.gif
DaShujufenxiJishuYuYingyongYizhanshiXuexiCYuyanBianchengWangFix1/img/menu-icon.png
da_shujufenxi_jishu_yu_yingyong_yizhanshi_xuexi_c_yuyan_biancheng_wang_fix1-2025.3.24.1.dist-info/METADATA
da_shujufenxi_jishu_yu_yingyong_yizhanshi_xuexi_c_yuyan_biancheng_wang_fix1-2025.3.24.1.dist-info/WHEEL
da_shujufenxi_jishu_yu_yingyong_yizhanshi_xuexi_c_yuyan_biancheng_wang_fix1-2025.3.24.1.dist-info/entry_points.txt
da_shujufenxi_jishu_yu_yingyong_yizhanshi_xuexi_c_yuyan_biancheng_wang_fix1-2025.3.24.1.dist-info/top_level.txt
da_shujufenxi_jishu_yu_yingyong_yizhanshi_xuexi_c_yuyan_biancheng_wang_fix1-2025.3.24.1.dist-info/RECORD
